AutoOpInspect/__init__.py
AutoOpInspect/module_print.py
AutoOpInspect/ops_info.py
AutoOpInspect/utils.py
auto_op_inspect-1.0.dist-info/LICENSE
auto_op_inspect-1.0.dist-info/METADATA
auto_op_inspect-1.0.dist-info/WHEEL
auto_op_inspect-1.0.dist-info/top_level.txt
auto_op_inspect-1.0.dist-info/RECORD
