Metadata-Version: 2.1
Name: auto-op-inspect
Version: 1.0
Summary: AutoOpInspect is a Python tool designed to facilitate the inspection and profiling of operators within PyTorch models, aiming to assist machine learning developers, researchers, and enthusiasts in debugging, optimizing, and understanding PyTorch models more efficiently and effectively.
Home-page: https://github.com/ThibaultCastells/AutoOpInspect
Author: Thibault Castells
License: MIT
Classifier: Development Status :: 3 - Alpha
Classifier: Intended Audience :: Developers
Classifier: Intended Audience :: Science/Research
Classifier: License :: OSI Approved :: MIT License
Classifier: Programming Language :: Python :: 3
Classifier: Topic :: Software Development :: Libraries :: Python Modules
Requires-Python: >=3.6
License-File: LICENSE
Requires-Dist: torch
Requires-Dist: tqdm
